FahrenCels/__init__.py
fahrencels-0.1.1.dist-info/licenses/LICENSE
fahrencels-0.1.1.dist-info/METADATA
fahrencels-0.1.1.dist-info/WHEEL
fahrencels-0.1.1.dist-info/top_level.txt
fahrencels-0.1.1.dist-info/RECORD
