Metadata-Version: 2.4
Name: FahrenCels
Version: 0.1.1
Summary: A simple Python module for converting temperatures between Celsius and Fahrenheit.
Author: annzelly
Classifier: Programming Language :: Python :: 3
Classifier: Operating System :: OS Independent
Requires-Python: >=3.6
License-File: LICENSE
Requires-Dist: requests
Requires-Dist: numpy
Dynamic: author
Dynamic: classifier
Dynamic: description
Dynamic: description-content-type
Dynamic: license-file
Dynamic: requires-dist
Dynamic: requires-python
Dynamic: summary
